rest_txt/__init__.py
rest_txt/_util.py
rest_txt/config.py
rest_txt/handlers.py
rest_txt/db/text.py
rest_txt-0.0.1.dist-info/licenses/LICENSE.txt
rest_txt-0.0.1.dist-info/METADATA
rest_txt-0.0.1.dist-info/WHEEL
rest_txt-0.0.1.dist-info/top_level.txt
rest_txt-0.0.1.dist-info/RECORD
