Metadata-Version: 2.4
Name: rest_txt
Version: 0.0.1
License-Expression: MIT
Project-URL: repository, https://github.com/chrisvanrijn/rest_txt
License-File: LICENSE.txt
Requires-Dist: werkzeug
Dynamic: license-file
